{
  "mode": "pre",
  "tag": "alpha",
  "initialVersions": {
    "@launchpad-ui/remix": "0.0.1",
    "@launchpad-ui/alert": "0.8.4",
    "@launchpad-ui/avatar": "0.6.4",
    "@launchpad-ui/banner": "0.10.4",
    "@launchpad-ui/button": "0.11.4",
    "@launchpad-ui/card": "0.2.4",
    "@launchpad-ui/chip": "0.9.4",
    "@launchpad-ui/clipboard": "0.11.4",
    "@launchpad-ui/collapsible": "0.1.35",
    "@launchpad-ui/columns": "0.1.9-alpha.0",
    "@launchpad-ui/core": "0.47.4",
    "@launchpad-ui/counter": "0.4.3-alpha.0",
    "@launchpad-ui/data-table": "0.2.3-alpha.0",
    "@launchpad-ui/drawer": "0.5.4",
    "@launchpad-ui/dropdown": "0.6.78",
    "@launchpad-ui/filter": "0.6.4",
    "@launchpad-ui/focus-trap": "0.1.13",
    "@launchpad-ui/form": "0.10.4",
    "@launchpad-ui/icons": "0.14.4",
    "@launchpad-ui/inline": "0.1.9-alpha.0",
    "@launchpad-ui/inline-edit": "0.2.4",
    "@launchpad-ui/markdown": "0.5.3-alpha.0",
    "@launchpad-ui/menu": "0.12.4",
    "@launchpad-ui/modal": "0.17.4",
    "@launchpad-ui/navigation": "0.12.4",
    "@launchpad-ui/overlay": "0.3.29",
    "@launchpad-ui/pagination": "0.4.4",
    "@launchpad-ui/popover": "0.11.3-alpha.0",
    "@launchpad-ui/portal": "0.1.4",
    "@launchpad-ui/progress": "0.5.34-alpha.0",
    "@launchpad-ui/progress-bubbles": "0.7.3-alpha.0",
    "@launchpad-ui/select": "0.4.4",
    "@launchpad-ui/slider": "0.5.3-alpha.0",
    "@launchpad-ui/snackbar": "0.4.4",
    "@launchpad-ui/split-button": "0.9.4",
    "@launchpad-ui/stack": "0.1.9-alpha.0",
    "@launchpad-ui/tab-list": "0.5.3-alpha.0",
    "@launchpad-ui/table": "0.6.3-alpha.0",
    "@launchpad-ui/tag": "0.3.4",
    "@launchpad-ui/toast": "0.3.4",
    "@launchpad-ui/toggle": "0.7.3-alpha.0",
    "@launchpad-ui/tokens": "0.9.0-alpha.1",
    "@launchpad-ui/tooltip": "0.8.3-alpha.0",
    "@launchpad-ui/types": "0.1.0",
    "@launchpad-ui/vars": "0.2.6-alpha.0"
  },
  "changesets": [
    "cyan-donkeys-change",
    "quick-apples-happen",
    "quick-rockets-sit",
    "quiet-emus-teach",
    "selfish-pens-mate",
    "thick-radios-report",
    "warm-papayas-hear",
    "wise-buckets-deliver"
  ]
}
